expediagroup/sdk/fraudpreventionv2/__init__.py
openworld_sdk_python_fraudpreventionv2-2.0.0.dist-info/METADATA
openworld_sdk_python_fraudpreventionv2-2.0.0.dist-info/WHEEL
openworld_sdk_python_fraudpreventionv2-2.0.0.dist-info/top_level.txt
openworld_sdk_python_fraudpreventionv2-2.0.0.dist-info/RECORD
