Metadata-Version: 2.1
Name: openworld-sdk-python-fraudpreventionv2
Version: 2.0.0
Summary: Expedia Group Fraud Prevention V2 SDK for Python
Requires-Dist: expediagroup-fraudpreventionv2-sdk
